velopy.py
velopy-0.1.4.dist-info/LICENSE.txt
velopy-0.1.4.dist-info/METADATA
velopy-0.1.4.dist-info/WHEEL
velopy-0.1.4.dist-info/top_level.txt
velopy-0.1.4.dist-info/RECORD
