Metadata-Version: 2.1
Name: velopy
Version: 0.1.4
Summary: Library for simple calculations with respect to road cycling and training
Home-page: https://gitlab.com/ce72/velo/-/tree/master
Author: Christoph Ernst
License: BSD New License
Keywords: cycling,training with power,training zones,TSS,PMC,CTL,ATL,power model
Platform: UNKNOWN
Requires-Python: >3.6
